fuzzytri/examples/advanced_operations.py
fuzzytri/examples/basic_usage.py
fuzzytri/fuzzytri/__init__.py
fuzzytri/fuzzytri/alphacut.py
fuzzytri/fuzzytri/core.py
fuzzytri/fuzzytri/exceptions.py
fuzzytri/fuzzytri/operations.py
fuzzytri/fuzzytri/utils.py
fuzzytri/tests/test_alpha.py
fuzzytri/tests/test_core.py
fuzzytri/tests/test_operations.py
fuzzytri/tests/test_utils.py
fuzzytri-1.1.0.dist-info/licenses/LICENSE
fuzzytri-1.1.0.dist-info/METADATA
fuzzytri-1.1.0.dist-info/WHEEL
fuzzytri-1.1.0.dist-info/top_level.txt
fuzzytri-1.1.0.dist-info/RECORD
