Metadata-Version: 2.4
Name: fuzzytri
Version: 1.1.0
Summary: Noravshan mantiq nazariyasi va amaliyoti uchun Python kutubxonasi
Author-email: FuzzyTri Team <fuzzytri@example.com>
Project-URL: Homepage, https://github.com/username/fuzzytri
Project-URL: Documentation, https://fuzzytri.readthedocs.io
Project-URL: Repository, https://github.com/username/fuzzytri
Project-URL: Issue Tracker, https://github.com/username/fuzzytri/issues
Keywords: fuzzy,logic,noravshan,vector,mathematics
Classifier: Development Status :: 4 - Beta
Classifier: Intended Audience :: Education
Classifier: Intended Audience :: Science/Research
Classifier: License :: OSI Approved :: MIT License
Classifier: Operating System :: OS Independent
Classifier: Programming Language :: Python :: 3
Classifier: Programming Language :: Python :: 3.8
Classifier: Programming Language :: Python :: 3.9
Classifier: Programming Language :: Python :: 3.10
Classifier: Programming Language :: Python :: 3.11
Classifier: Topic :: Scientific/Engineering :: Mathematics
Classifier: Topic :: Software Development :: Libraries :: Python Modules
Requires-Python: >=3.8
License-File: LICENSE
Provides-Extra: dev
Requires-Dist: pytest>=6.0; extra == "dev"
Requires-Dist: pytest-cov; extra == "dev"
Requires-Dist: black; extra == "dev"
Requires-Dist: flake8; extra == "dev"
Requires-Dist: mypy; extra == "dev"
Provides-Extra: docs
Requires-Dist: sphinx; extra == "docs"
Requires-Dist: sphinx-rtd-theme; extra == "docs"
Dynamic: license-file
